tsbrowse/__init__.py
tsbrowse/__main__.py
tsbrowse/_version.py
tsbrowse/app.py
tsbrowse/config.py
tsbrowse/jit.py
tsbrowse/model.py
tsbrowse/plot_helpers.py
tsbrowse/preprocess.py
tsbrowse/raster.py
tsbrowse/pages/__init__.py
tsbrowse/pages/edges.py
tsbrowse/pages/mutations.py
tsbrowse/pages/nodes.py
tsbrowse/pages/overview.py
tsbrowse/pages/tables.py
tsbrowse/pages/trees.py
tsbrowse-0.0.3.dist-info/licenses/LICENSE
tsbrowse-0.0.3.dist-info/METADATA
tsbrowse-0.0.3.dist-info/WHEEL
tsbrowse-0.0.3.dist-info/top_level.txt
tsbrowse-0.0.3.dist-info/RECORD
