Metadata-Version: 2.4
Name: tsbrowse
Version: 0.0.3
Summary: Webapp to view and visualise the information structure in tskit ARGs
Home-page: https://tskit.dev/tsbrowse/
Author: Tskit Developers
Author-email: Tskit Developers <admin@tskit.dev>
License: MIT
Project-URL: Bug Tracker, https://github.com/tskit-dev/tsbrowse/issues
Project-URL: Source Code, https://github.com/tskit-dev/tsbrowse
Project-URL: Homepage, https://tskit.dev/tsbrowse/
Keywords: tree sequence,ancestral recombination graph,tskit,quality control
Platform: POSIX
Platform: Windows
Platform: MacOS X
Classifier: Intended Audience :: Science/Research
Classifier: License :: OSI Approved :: MIT License
Classifier: Programming Language :: Python :: 3
Classifier: Topic :: Scientific/Engineering
Classifier: Topic :: Scientific/Engineering :: Bio-Informatics
Requires-Python: >=3.10
License-File: LICENSE
Requires-Dist: click
Requires-Dist: daiquiri
Requires-Dist: panel<=1.6.1,>=1.5.2
Requires-Dist: hvplot
Requires-Dist: datashader>=0.16.3
Requires-Dist: matplotlib
Requires-Dist: tskit
Requires-Dist: tszip
Dynamic: license-file
